[
    {
        "img":"https://i.ibb.co/DrFzQN9/image-8.png",
        "title":"Logitech G203 Wired 8000 DPI For PC/Mac",
        "star":[
            {
                "star_img":"https://i.ibb.co/cvPn2k9/Vector.png",
                "star_img":"https://i.ibb.co/cvPn2k9/Vector.png",
                "star_img":"https://i.ibb.co/cvPn2k9/Vector.png",
                "star_img":"https://i.ibb.co/cvPn2k9/Vector.png"
            }
        ],
        "review": "(1 review)",
        "price": "$290.00",
        "available": "In stock",
        "quantity": "10 Products"
    },
    {
        "img":"https://i.ibb.co/gv858RH/image-8-1.png",
        "title":"Samsung Galaxy S21 Ultra 128GB - Black",
        "star":[
            {
                "star_img":"https://i.ibb.co/cvPn2k9/Vector.png",
                "star_img":"https://i.ibb.co/cvPn2k9/Vector.png",
                "star_img":"https://i.ibb.co/cvPn2k9/Vector.png",
                "star_img":"https://i.ibb.co/cvPn2k9/Vector.png"
            }
        ],
        "review": "(5 review)",
        "price": "$290.00",
        "available": "In stock",
        "quantity": "17 Products"
    },
    {
        "img":"https://i.ibb.co/64QkbHz/image-8-2.png",
        "title":"Apple iPad Pro M1 11-inch 2021 Wi-Fi 128GB",
        "star":[
            {
                "star_img":"https://i.ibb.co/cvPn2k9/Vector.png",
                "star_img":"https://i.ibb.co/cvPn2k9/Vector.png",
                "star_img":"https://i.ibb.co/cvPn2k9/Vector.png",
                "star_img":"https://i.ibb.co/cvPn2k9/Vector.png"
            }
        ],
        "review": "(6 review)",
        "price": "$290.00",
        "available": "In stock",
        "quantity": "10 Products"
    },
    {
        "img":"https://i.ibb.co/nPtYMm1/image-8-3.png",
        "title":"Logitech G203 Wired 8000 DPI For PC/Mac",
        "star":[
            {
                "star_img":"https://i.ibb.co/cvPn2k9/Vector.png",
                "star_img":"https://i.ibb.co/cvPn2k9/Vector.png",
                "star_img":"https://i.ibb.co/cvPn2k9/Vector.png",
                "star_img":"https://i.ibb.co/cvPn2k9/Vector.png"
            }
        ],
        "review": "(8 review)",
        "price": "$290.00",
        "no_available": "Out of Stock",
        "quantity": "0 Products"
    },
    {
        "img":"https://i.ibb.co/M6XDd1k/image-8-4.png",
        "title":"Logitech G203 Wired 8000 DPI For PC/Mac",
        "star":[
            {
                "star_img":"https://i.ibb.co/cvPn2k9/Vector.png",
                "star_img":"https://i.ibb.co/cvPn2k9/Vector.png",
                "star_img":"https://i.ibb.co/cvPn2k9/Vector.png",
                "star_img":"https://i.ibb.co/cvPn2k9/Vector.png"
            }
        ],
        "review": "(1 review)",
        "price": "$290.00",
        "available": "In stock",
        "quantity": "10 Products"
    },
    {
        "img":"https://i.ibb.co/ZhrKhJQ/image-8-5.png",
        "title":"Samsung Galaxy S21 Ultra 128GB - Black",
        "star":[
            {
                "star_img":"https://i.ibb.co/cvPn2k9/Vector.png",
                "star_img":"https://i.ibb.co/cvPn2k9/Vector.png",
                "star_img":"https://i.ibb.co/cvPn2k9/Vector.png",
                "star_img":"https://i.ibb.co/T0KKmp4/Vector-1.png"
            }
        ],
        "review": "(1 review)",
        "price": "$290.00",
        "available": "In stock",
        "quantity": "17 Products"
    },
    {
        "img":"https://i.ibb.co/ZNd4D06/image-8-6.png",
        "title":"Apple iPad Pro M1 11-inch 2021 Wi-Fi 128GB",
        "star":[
            {
                "star_img":"https://i.ibb.co/cvPn2k9/Vector.png",
                "star_img":"https://i.ibb.co/cvPn2k9/Vector.png",
                "star_img":"https://i.ibb.co/cvPn2k9/Vector.png",
                "star_img":"https://i.ibb.co/T0KKmp4/Vector-1.png"
            }
        ],
        "review": "(6 review)",
        "price": "$290.00",
        "available": "In stock",
        "quantity": "12 Products"
    },
    {
        "img":"Apple iPad Pro M1 11-inch 2021 Wi-Fi 128GB",
        "title":"Logitech G203 Wired 8000 DPI For PC/Mac",
        "star":[
            {
                "star_img":"https://i.ibb.co/cvPn2k9/Vector.png",
                "star_img":"https://i.ibb.co/cvPn2k9/Vector.png",
                "star_img":"https://i.ibb.co/cvPn2k9/Vector.png",
                "star_img":"https://i.ibb.co/cvPn2k9/Vector.png"
            }
        ],
        "review": "(1 review)",
        "price": "$290.00",
        "available": "In stock",
        "quantity": "10 Products"
    },
    {
        "img":"https://i.ibb.co/s565sYz/image-8-8.png",
        "title":"Logitech G203 Wired 8000 DPI For PC/Mac",
        "star":[
            {
                "star_img":"https://i.ibb.co/cvPn2k9/Vector.png",
                "star_img":"https://i.ibb.co/cvPn2k9/Vector.png",
                "star_img":"https://i.ibb.co/cvPn2k9/Vector.png",
                "star_img":"https://i.ibb.co/cvPn2k9/Vector.png"
            }
        ],
        "review": "(1 review)",
        "price": "$290.00",
        "available": "In stock",
        "quantity": "10 Products"
    },
    {
        "img":"https://i.ibb.co/mhwv1N4/image-8-9.png",
        "title":"Samsung Galaxy S21 Ultra 128GB - Black",
        "star":[
            {
                "star_img":"https://i.ibb.co/cvPn2k9/Vector.png",
                "star_img":"https://i.ibb.co/cvPn2k9/Vector.png",
                "star_img":"https://i.ibb.co/cvPn2k9/Vector.png",
                "star_img":"https://i.ibb.co/T0KKmp4/Vector-1.png"
            }
        ],
        "review": "(1 review)",
        "price": "$290.00",
        "available": "In stock",
        "quantity": "10 Products"
    },
    {
        "img":"https://i.ibb.co/YcvYm9P/image-8-10.png",
        "title":"Apple iPad Pro M1 11-inch 2021 Wi-Fi 128GB",
        "star":[
            {
                "star_img":"https://i.ibb.co/cvPn2k9/Vector.png",
                "star_img":"https://i.ibb.co/cvPn2k9/Vector.png",
                "star_img":"https://i.ibb.co/cvPn2k9/Vector.png",
                "star_img":"https://i.ibb.co/cvPn2k9/Vector.png"
            }
        ],
        "review": "(1 review)",
        "price": "$290.00",
        "available": "In stock",
        "quantity": "10 Products"
    },
    {
        "img":"https://i.ibb.co/nPtYMm1/image-8-3.png",
        "title":"Logitech G203 Wired 8000 DPI For PC/Mac",
        "star":[
            {
                "star_img":"https://i.ibb.co/cvPn2k9/Vector.png",
                "star_img":"https://i.ibb.co/cvPn2k9/Vector.png",
                "star_img":"https://i.ibb.co/cvPn2k9/Vector.png",
                "star_img":"https://i.ibb.co/cvPn2k9/Vector.png"
            }
        ],
        "review": "(1 review)",
        "price": "$290.00",
        "available": "In stock",
        "quantity": "10 Products"
    }
]